trent/__init__.py
trent/coll.py
trent/coll_aux.py
trent/concur.py
trent/func.py
trent/interface.py
trent/nth.py
trent/pcoll.py
trent-0.4.1.dist-info/licenses/LICENSE
trent-0.4.1.dist-info/METADATA
trent-0.4.1.dist-info/WHEEL
trent-0.4.1.dist-info/top_level.txt
trent-0.4.1.dist-info/RECORD
