Metadata-Version: 2.4
Name: trent
Version: 0.4.1
Summary: Convenient Sequence/Iterable/Collection processing for python. Inspired by Clojure mapping and threading macros.
Author-email: Vasyl Tsiura <morfey.rulit@gmail.com>
Maintainer-email: Vasyl Tsiura <morfey.rulit@gmail.com>
Project-URL: Homepage, https://github.com/VasilevsVV/trent
Project-URL: Issues, https://github.com/VasilevsVV/trent/issues
Keywords: Sequence,Collection,mapping,stream,functional,iteration,concurrency,group,by
Requires-Python: >=3.10.12
License-File: LICENSE
Requires-Dist: funcy
Requires-Dist: psutil
Dynamic: license-file
